src/__init__.py
src/main.py
src/scripts/__init__.py
src/scripts/create.py
src/scripts/run.py
src/scripts/update.py
tests/__init__.py
tests/dummy.py
dash_plotly_cli-0.1.dist-info/LICENSE
dash_plotly_cli-0.1.dist-info/METADATA
dash_plotly_cli-0.1.dist-info/WHEEL
dash_plotly_cli-0.1.dist-info/entry_points.txt
dash_plotly_cli-0.1.dist-info/top_level.txt
dash_plotly_cli-0.1.dist-info/RECORD
